[
 {
  "file": "images/book-4/diagrams/p001-1.jpg",
  "page": 1,
  "w": 1772,
  "h": 2717,
  "context": ""
 },
 {
  "file": "images/book-4/diagrams/p003-1.jpg",
  "page": 3,
  "w": 1196,
  "h": 1676,
  "context": ""
 },
 {
  "file": "images/book-4/diagrams/p004-1.jpg",
  "page": 4,
  "w": 1196,
  "h": 1676,
  "context": ""
 },
 {
  "file": "images/book-4/diagrams/p005-1.jpg",
  "page": 5,
  "w": 904,
  "h": 1280,
  "context": ""
 },
 {
  "file": "images/book-4/diagrams/p022-1.jpg",
  "page": 22,
  "w": 900,
  "h": 1351,
  "context": "7"
 },
 {
  "file": "images/book-4/diagrams/p024-1.jpg",
  "page": 24,
  "w": 825,
  "h": 1456,
  "context": "9"
 },
 {
  "file": "images/book-4/diagrams/p025-1.jpg",
  "page": 25,
  "w": 927,
  "h": 632,
  "context": "10 THE DEFINITION OF THE ANCIENT OF DAYS JESUS then drew an ANAGRAM and started to explain to Shekinaih and David, THE TRINITY’S DEFINITION of, “THE ANCIENT OF DAYS”. JESUS said, “The ANCIENT OF DAYS, consists of THE FATHER, THE HOLY SPIRIT and JESUS, represented by Shekinaih and Aaron K David, THE "
 },
 {
  "file": "images/book-4/diagrams/p026-1.jpg",
  "page": 26,
  "w": 928,
  "h": 645,
  "context": "11 THEREFORE, THIS IS THE: Shekinaih has been with THE FATHER and THE HOLY SPIRIT IN THE BEGINNING. So are you in ME IN THE BEGINNING. BOTH OF YOU EXISTED BEFORE ALL THINGS WERE CREATED IN THE BEGINNING. BOTH OF YOU ARE AN EXTENSION OF US IN THE BEGINNING. THE FATHER and THE HOLY SPIRIT, INCARNATE a"
 },
 {
  "file": "images/book-4/diagrams/p027-1.jpg",
  "page": 27,
  "w": 279,
  "h": 305,
  "context": "12 BOTH, THE NON-CREATED BEING AND THE CREATED BEING; NON-CREATED BEING IN THE FATHER, AND CREATED BEING IN THE HOLY SPIRIT. Son of man, don’t be wise in your own eyes. Thinking you know better with all the Theology in your mind; thereby causing you to miss Our Revelation of Our Existence together w"
 },
 {
  "file": "images/book-4/diagrams/p047-1.jpg",
  "page": 47,
  "w": 843,
  "h": 1308,
  "context": "32 ACT 1 SCENE 4 LEVEL 4 OF HELL/ HEAVEN"
 },
 {
  "file": "images/book-4/diagrams/p049-1.jpg",
  "page": 49,
  "w": 750,
  "h": 537,
  "context": "34 I then saw you and me inside a globe-like library, where the books of the deeds of all humanity were stored. I then saw us seated on THE GREAT WHITE THRONE. On the left where we were seated, there was a shelf filled with the books of the dead, whose works were recorded. I saw THE FATHER released "
 },
 {
  "file": "images/book-4/diagrams/p065-1.jpg",
  "page": 65,
  "w": 936,
  "h": 1404,
  "context": "50 6. BE SOBER"
 },
 {
  "file": "images/book-4/diagrams/p098-1.jpg",
  "page": 98,
  "w": 600,
  "h": 920,
  "context": "83 PART 5 ESCAPE THE TORMENT OF HELL FIRE IN LEVEL 1, 2, 3"
 },
 {
  "file": "images/book-4/diagrams/p132-1.jpg",
  "page": 132,
  "w": 792,
  "h": 1098,
  "context": "117 THE SEVEN LEVELS OF HELL/HEAVEN VISION OF THE SEVEN LEVELS OF HELL/HEAVEN"
 },
 {
  "file": "images/book-4/diagrams/p135-1.jpg",
  "page": 135,
  "w": 1019,
  "h": 1737,
  "context": "120"
 },
 {
  "file": "images/book-4/diagrams/p137-1.jpg",
  "page": 137,
  "w": 403,
  "h": 402,
  "context": "122 LEVEL 1, GEHENNA/TARTARUS (DAMNATION, ETERNAL FIRE, POINT OF NO RETURN) DAVID: ABBA FATHER, where is Gehenna? JESUS: Gehenna/Tartarus is made up of Gehenna with Tartarus indented below it. It is situated in the planet Venus. This place is damned with eternal fire and it’s a place of no return. V"
 },
 {
  "file": "images/book-4/diagrams/p137-2.jpg",
  "page": 137,
  "w": 926,
  "h": 303,
  "context": "122 LEVEL 1, GEHENNA/TARTARUS (DAMNATION, ETERNAL FIRE, POINT OF NO RETURN) DAVID: ABBA FATHER, where is Gehenna? JESUS: Gehenna/Tartarus is made up of Gehenna with Tartarus indented below it. It is situated in the planet Venus. This place is damned with eternal fire and it’s a place of no return. V"
 },
 {
  "file": "images/book-4/diagrams/p138-1.jpg",
  "page": 138,
  "w": 900,
  "h": 733,
  "context": "123 Act 19:27 So that not only this our craft is in danger to be set at nought; but also that the temple of the great goddess Diana should be despised, and her magnificence should be destroyed, whom all Asia and the world worshippeth. She is also known as Aphrodite and the Queen of Heaven, and is kn"
 },
 {
  "file": "images/book-4/diagrams/p139-1.jpg",
  "page": 139,
  "w": 815,
  "h": 557,
  "context": "124 Avoid her at all costs so as not to be tempted to commit fornication with her in this world and end up being locked up in Sheol. Pro 5:3 For the lips of a strange woman drop as an honeycomb, and her mouth is smoother than oil: Pro 5:4 But her offspring (H319 “achariyth” posterity, remnant, resid"
 },
 {
  "file": "images/book-4/diagrams/p142-1.jpg",
  "page": 142,
  "w": 989,
  "h": 596,
  "context": "127 Rev 14:12 Here is the patience of the saints: here are they that keep the commandments of God, and the faith of JESUS. 2) THE UNBELIEVING SHEKINAIH: I saw a vision of JESUS writing these word on a green board. “DOUBT = UNBELIEF = NO FAITH = LOSE ALL YOUR REWARDS = CURSES = GNASHING OF TEETH ETER"
 },
 {
  "file": "images/book-4/diagrams/p156-2.jpg",
  "page": 156,
  "w": 925,
  "h": 358,
  "context": "141 LEVEL 2, PERDITION 1) MEMBERS OF SECRET SOCIETIES THAT DO EVIL Immediately, I was teleported to Level 2 of Hell called Perdition. There I saw people from different secret societies who did evil and had sworn unto death with their blood unto their gods. JESUS then said to them, “All members of se"
 },
 {
  "file": "images/book-4/diagrams/p176-2.jpg",
  "page": 176,
  "w": 926,
  "h": 372,
  "context": "161 LEVEL 3, HADES/SHEOL Instantly, they were all teleported to Level 3 called Sheol/Hades. Upon arrival, a large crowd of dead souls with pale lifeless faces dressed up in Black Death garments were queuing up to be allotted in their predestined torturing allotment unit; while others were already in"
 },
 {
  "file": "images/book-4/diagrams/p184-1.jpg",
  "page": 184,
  "w": 880,
  "h": 740,
  "context": "169 LEVEL 4, THE GREAT WHITE THRONE After visiting Sheol, both Shekinaih and David were again teleported to Level 4, THE GREAT WHITE THRONE."
 },
 {
  "file": "images/book-4/diagrams/p186-1.jpg",
  "page": 186,
  "w": 550,
  "h": 458,
  "context": "171 LEVEL 5, ABADDON (THE BRIGHTER SIDE, FIRST LEVEL OF HEAVEN) After JESUS had finished explaining THE GREAT WHITE THRONE, they were teleported to Level 5, Abaddon. JESUS: Abaddon is a confined and restricted area, but it is in a much nicer environment. Everyone is still restricted within their com"
 },
 {
  "file": "images/book-4/diagrams/p186-2.jpg",
  "page": 186,
  "w": 1026,
  "h": 336,
  "context": "171 LEVEL 5, ABADDON (THE BRIGHTER SIDE, FIRST LEVEL OF HEAVEN) After JESUS had finished explaining THE GREAT WHITE THRONE, they were teleported to Level 5, Abaddon. JESUS: Abaddon is a confined and restricted area, but it is in a much nicer environment. Everyone is still restricted within their com"
 },
 {
  "file": "images/book-4/diagrams/p189-1.jpg",
  "page": 189,
  "w": 557,
  "h": 557,
  "context": "174 LEVEL 6, ABRAHAM’S CREEK (BOSOM) JESUS then said to them, “Now We shall go to Abraham’s Creek”. In a twinkling of an eye, they were teleported to Level 6, Abraham’s Creek. JESUS: Abraham’s Creek (Bosom) is also a protected area in another planet. The compounds are bigger than Level 5. Each perso"
 },
 {
  "file": "images/book-4/diagrams/p189-2.jpg",
  "page": 189,
  "w": 1021,
  "h": 340,
  "context": "174 LEVEL 6, ABRAHAM’S CREEK (BOSOM) JESUS then said to them, “Now We shall go to Abraham’s Creek”. In a twinkling of an eye, they were teleported to Level 6, Abraham’s Creek. JESUS: Abraham’s Creek (Bosom) is also a protected area in another planet. The compounds are bigger than Level 5. Each perso"
 },
 {
  "file": "images/book-4/diagrams/p191-2.jpg",
  "page": 191,
  "w": 1021,
  "h": 439,
  "context": "176 LEVEL 7, THE THIRD HEAVEN/PARADISE JESUS then turned to David and said to him, “Now We shall go to Level 7, Paradise”. Immediately, they were all in Paradise. DAVID: ABBA FATHER, is Paradise the third heaven that Paul mentioned? 2 Co 12:1 It is not expedient for me doubtless to glory. I will com"
 },
 {
  "file": "images/book-4/diagrams/p201-1.jpg",
  "page": 201,
  "w": 980,
  "h": 579,
  "context": "186 THE SEVEN CONTINENTS JESUS: Now, I will show you how We will judge the seven continents according to the people, the culture, the political arena and the influence sector."
 },
 {
  "file": "images/book-4/diagrams/p202-1.jpg",
  "page": 202,
  "w": 976,
  "h": 612,
  "context": "187 1) AFRICA Africa is a corrupted continent and also the most bullied. There are many vices to spice life. In the last days, while most parts of the world will be under the water due to earthquakes, volcano eruptions, asteroids and tsunamis, Uganda and its neighboring countries where My remnant is"
 },
 {
  "file": "images/book-4/diagrams/p204-1.jpg",
  "page": 204,
  "w": 977,
  "h": 611,
  "context": "189 2) THE UNITED KINGDOM SHEKINAIH: I saw the map of the United Kingdom. Only the Scottish Highlands remained and the rest went under water after mega earthquakes, volcano eruptions and tsunamis hit them. I saw most low-rise buildings were completely covered with water for days and months. A lot of"
 },
 {
  "file": "images/book-4/diagrams/p207-1.jpg",
  "page": 207,
  "w": 977,
  "h": 611,
  "context": "192 3) SINGAPORE, MALAYSIA, SOUTH EAST ASIA, ASIA MINOR A) PEOPLE SHEKINAIH: I saw the map of Singapore was very bright but some parts of the South East Asia Countries went below water because of tsunamis. I saw Terengganu and the left part of Penang Island were below water for a long time. I saw th"
 },
 {
  "file": "images/book-4/diagrams/p209-1.jpg",
  "page": 209,
  "w": 880,
  "h": 551,
  "context": "194 4) USA-NORTH AMERICA AND SOUTH AMERICA CONTINENT, CANADA AND NORTHERN HEMISPHERE"
 },
 {
  "file": "images/book-4/diagrams/p209-2.jpg",
  "page": 209,
  "w": 880,
  "h": 557,
  "context": "194 4) USA-NORTH AMERICA AND SOUTH AMERICA CONTINENT, CANADA AND NORTHERN HEMISPHERE"
 },
 {
  "file": "images/book-4/diagrams/p210-1.jpg",
  "page": 210,
  "w": 960,
  "h": 1441,
  "context": "195"
 },
 {
  "file": "images/book-4/diagrams/p212-1.jpg",
  "page": 212,
  "w": 976,
  "h": 608,
  "context": "197 SHEKINAIH: He wrote these words regarding Europe, “55% RUINED, 45% SPARED, BOTH LAND AND HIS PEOPLE”. A) PEOPLE JESUS: There are in total only a FEW HUNDRED BRIDE(S) IN EUROPE. My true virgins who are faithful to Me during the tribulation even unto death. They will not deny Me. SHEKINAIH: I hear"
 },
 {
  "file": "images/book-4/diagrams/p216-1.jpg",
  "page": 216,
  "w": 977,
  "h": 613,
  "context": "201 6) AUSTRALIA, NEW ZEALAND AND THE ISLANDS AROUND THE SOUTHERN HEMISPHERE SHEKINAIH: I saw half of Australia on the right sitting on a white cloth and as JESUS pulled the white cloth, half of Australia on the eastern side glided into the ocean, and were covered with water for a long time. I also "
 },
 {
  "file": "images/book-4/diagrams/p218-1.jpg",
  "page": 218,
  "w": 960,
  "h": 600,
  "context": "203 7) CHINA AND THE TOP RIGHT CORNER (QUADRANT) OF NORTHERN HEMISPHERE JESUS: The whole Northern Hemisphere will be badly ruined. 70% OF THE POPULATION WILL BE KILLED. ALASKA AND CANADA WILL BE COVERED WITH WATER BECAUSE OF THE MELTING POLAR ICE. SHEKINAIH: I saw a comet hitting Tianjin. I also saw"
 },
 {
  "file": "images/book-4/diagrams/p221-1.jpg",
  "page": 221,
  "w": 960,
  "h": 598,
  "context": "206 THE FIVE MAIN COUNTRIES 1) AMERICA A) POWER OF ANTI-CHRIST SHEKINAIH: I saw a man in green military uniform closing one eye. I saw the word, “FOR HUMAN EXPERIMENT, PERMISSION GRANTED IN EXCHANGE FOR ALIEN TECHNOLOGY”. JESUS: I will disable them in the last days. SHEKINAIH: I saw JESUS wrote, “AL"
 },
 {
  "file": "images/book-4/diagrams/p224-1.jpg",
  "page": 224,
  "w": 992,
  "h": 765,
  "context": "209"
 },
 {
  "file": "images/book-4/diagrams/p224-2.jpg",
  "page": 224,
  "w": 1099,
  "h": 777,
  "context": "209"
 },
 {
  "file": "images/book-4/diagrams/p225-1.jpg",
  "page": 225,
  "w": 960,
  "h": 871,
  "context": "210 THE SEVEN-HEADED BEAST One of the heads of the beast is the authority that controls Greater China. For a time and a season, the dragon will give authority unto that particular head of the beast to be his spokesman. The other beast that will come out of the earth having two horns like a lamb and "
 },
 {
  "file": "images/book-4/diagrams/p234-1.jpg",
  "page": 234,
  "w": 900,
  "h": 1528,
  "context": "219"
 },
 {
  "file": "images/book-4/diagrams/p236-1.jpg",
  "page": 236,
  "w": 787,
  "h": 581,
  "context": "221 As each person chose their box, it turned into an oval shaped holding mirror. Those who thought that they were beautiful in their character and chose the box with the word, “Beautiful”, written on it, but in actual fact JESUS saw them as very ugly and wicked. They were shocked when judgment were"
 },
 {
  "file": "images/book-4/diagrams/p236-2.jpg",
  "page": 236,
  "w": 550,
  "h": 550,
  "context": "221 As each person chose their box, it turned into an oval shaped holding mirror. Those who thought that they were beautiful in their character and chose the box with the word, “Beautiful”, written on it, but in actual fact JESUS saw them as very ugly and wicked. They were shocked when judgment were"
 },
 {
  "file": "images/book-4/diagrams/p238-1.jpg",
  "page": 238,
  "w": 928,
  "h": 604,
  "context": "223 2) VISION OF A TRAIN STATION SHEKINAIH: I saw a vision of me in my Golden Empress robe representing THE FATHER and THE HOLY SPIRIT, like a father/mother standing next to JESUS, whose height is at my womb level. With my hand on his hand, We began to pour a green vase full of penguins upon the ear"
 },
 {
  "file": "images/book-4/diagrams/p239-1.jpg",
  "page": 239,
  "w": 1051,
  "h": 452,
  "context": "224 I saw Jesus in me, began to distribute test papers to all these children who were seated in front of tables in front of them. He, through me, then collected all their test papers and I started to mark them. Those who passed ended up in Level 5 and 6, and majority of the MOST YIELDED GROUP was se"
 },
 {
  "file": "images/book-4/diagrams/p240-1.jpg",
  "page": 240,
  "w": 875,
  "h": 1311,
  "context": "225 (SIMEON) in a 45 degree downward slope and then plunge 90 degree vertically into TARTARUS, THE LAKE OF FIRE."
 },
 {
  "file": "images/book-4/diagrams/p241-1.jpg",
  "page": 241,
  "w": 411,
  "h": 341,
  "context": "226 Then, I saw myself in the Golden Empress robe, correcting, reprimanding and disciplining a child who failed unto repentance and after he sincerely repented, I used the water hose to wash away all the shit, black maggots, snakes and all forms of defilements out of him. I then poured spiritual ker"
 },
 {
  "file": "images/book-4/diagrams/p241-2.jpg",
  "page": 241,
  "w": 447,
  "h": 360,
  "context": "226 Then, I saw myself in the Golden Empress robe, correcting, reprimanding and disciplining a child who failed unto repentance and after he sincerely repented, I used the water hose to wash away all the shit, black maggots, snakes and all forms of defilements out of him. I then poured spiritual ker"
 },
 {
  "file": "images/book-4/diagrams/p242-1.jpg",
  "page": 242,
  "w": 1080,
  "h": 600,
  "context": "227 Some landed on the forest and had their parachutes entangled on trees. Some landed badly on the ground and broke their legs."
 },
 {
  "file": "images/book-4/diagrams/p242-2.jpg",
  "page": 242,
  "w": 433,
  "h": 294,
  "context": "227 Some landed on the forest and had their parachutes entangled on trees. Some landed badly on the ground and broke their legs."
 },
 {
  "file": "images/book-4/diagrams/p243-2.jpg",
  "page": 243,
  "w": 995,
  "h": 606,
  "context": "228 Some dropped into the middle of the sea. Some who followed proper instructions landed safely unhurt. JESUS: In real tests, there will be casualties. “ONLY THOSE WHO ARE 100% YIELDED WILL REMAIN UNSCRATCHED”."
 },
 {
  "file": "images/book-4/diagrams/p250-1.jpg",
  "page": 250,
  "w": 879,
  "h": 1381,
  "context": "235"
 },
 {
  "file": "images/book-4/diagrams/p255-1.jpg",
  "page": 255,
  "w": 1045,
  "h": 1273,
  "context": "240 HANDOVER DECLARATION Receiving back the authority on behalf of THE TRINITY"
 },
 {
  "file": "images/book-4/diagrams/p256-1.jpg",
  "page": 256,
  "w": 1057,
  "h": 1312,
  "context": "241"
 },
 {
  "file": "images/book-4/diagrams/p259-1.jpg",
  "page": 259,
  "w": 1038,
  "h": 1391,
  "context": "244 BOOKS 1 & 2"
 },
 {
  "file": "images/book-4/diagrams/p261-1.jpg",
  "page": 261,
  "w": 780,
  "h": 609,
  "context": "246 BOOK 5"
 }
]